Metadata-Version: 2.4
Name: iflow-mcp_kukapay_pumpswap-mcp
Version: 0.1.0
Summary: An MCP server that enables AI agents to interact with PumpSwap for real-time token swaps and automated on-chain trading.
Requires-Python: >=3.13
License-File: LICENSE
Requires-Dist: mcp[cli]>=1.7.1
Requires-Dist: pumpswap-sdk>=0.1.3
Dynamic: license-file
